{"collect":[["fire","air","energy"],["energy","water","steam"],["energy","energy","none"],["energy","steam","none"],["air","earth","dust"],["fire","dust","gunpowder"],["gunpowder","energy","none"],["water","fire","steam"],["gunpowder","dust","none"],["air","gunpowder","none"],["earth","earth","pressure"],["pressure","dust","none"],["earth","dust","none"],["water","pressure","none"],["steam","pressure","none"],["fire","pressure","none"],["water","water","sea"],["fire","fire","none"],["air","air","pressure"],["dust","dust","none"],["gunpowder","gunpowder","none"],["energy","pressure","none"],["sea","sea","ocean"],["ocean","ocean","none"],["ocean","sea","none"],["water","sea","ocean"],["fire","sea","salt"],["salt","energy","none"],["salt","salt","none"],["steam","steam","none"],["fire","fire","none"],["salt","ocean","none"],["pressure","ocean","none"],["dust","salt","none"],["gunpowder","salt","none"],["gunpowder","steam","none"],["earth","water","mud"],["mud","ocean","none"],["water","fire","steam"],["mud","salt","none"],["steam","pressure","none"],["sea","water","ocean"],["air","air","pressure"],["energy","pressure","none"],["pressure","salt","none"],["mud","pressure","none"],["pressure","water","none"],["sea","steam","none"],["salt","mud","none"],["mud","pressure","none"],["dust","dust","none"],["gunpowder","gunpowder","none"],["ocean","water","none"],["earth","air","dust"],["steam","water","none"],["mud","fire","brick"],["earth","brick","none"],["brick","brick","wall"],["wall","wall","house"],["house","house","village"],["village","village","city"],["city","city","none"],["house","city","none"],["city","earth","none"],["water","house","none"],["brick","brick","wall"],["mud","brick","none"],["city","salt","none"],["village","city","none"],["city","house","none"],["wall","water","none"],["wall","fire","none"],["city","energy","none"],["air","earth","dust"],["earth","fire","lava"],["lava","water","obsidian"],["fire","obsidian","none"],["obsidian","obsidian","none"],["pressure","obsidian","none"],["lava","lava","none"],["wall","lava","none"],["obsidian","lava","none"],["water","earth","mud"],["fire","air","energy"],["earth","fire","lava"],["air","water","rain"],["rain","rain","flood"],["flood","village","none"],["flood","flood","none"],["air","energy","wind"],["wind","wind","none"],["gunpowder","wind","none"],["pressure","salt","none"],["wall","wind","none"],["wind","sea","wave"],["wave","wind","none"],["wave","lava","none"],["lava","lava","none"],["city","wind","none"],["wave","brick","none"],["village","steam","none"],["water","sea","ocean"],["gunpowder","earth","none"],["house","wind","windmill"],["windmill","fire","none"],["windmill","windmill","none"],["village","windmill","none"],["ocean","lava","none"],["obsidian","lava","none"],["house","windmill","none"],["windmill","city","none"],["salt","windmill","none"],["wave","windmill","none"],["steam","rain","none"],["wall","rain","none"],["air","windmill","none"],["sea","water","ocean"],["air","earth","dust"],["fire","earth","lava"],["air","water","rain"],["air","wind","none"],["air","air","pressure"],["pressure","windmill","none"],["wind","village","none"],["village","village","city"],["city","wall","none"],["city","village","none"]],"elements":["energy","steam","dust","gunpowder","pressure","sea","ocean","salt","mud","brick","wall","house","village","city","lava","obsidian","rain","flood","wind","wave","windmill"],"money":"2.50","age":20,"gender":1,"turkid":"25/05/2015"}